bootstrap.py
buildout.cfg
license.txt
setup.py
resolve/__init__.py
resolve/license.txt
resolve/readme.txt
resolve/version.txt
resolve.egg-info/PKG-INFO
resolve.egg-info/SOURCES.txt
resolve.egg-info/dependency_links.txt
resolve.egg-info/not-zip-safe
resolve.egg-info/top_level.txt
resolve/tests/__init__.py
resolve/tests/test_docs.py