Metadata-Version: 1.0
Name: resolve
Version: 1.0.0
Summary: Resolves strings containing dotted names into their objects.
Home-page: http://www.simplistix.co.uk/software/python/resolve
Author: Chris Withers
Author-email: chris@simplistix.co.uk
License: MIT
Platform: UNKNOWN
Classifier: Development Status :: 5 - Production/Stable
Classifier: Intended Audience :: Developers
Classifier: License :: OSI Approved :: MIT License
